adobe_cja_mcp/__init__.py
adobe_cja_mcp/server.py
adobe_cja_mcp/auth/__init__.py
adobe_cja_mcp/auth/oauth.py
adobe_cja_mcp/client/__init__.py
adobe_cja_mcp/client/cja_client.py
adobe_cja_mcp/models/__init__.py
adobe_cja_mcp/models/schemas.py
adobe_cja_mcp/tools/__init__.py
adobe_cja_mcp/tools/advanced_reporting.py
adobe_cja_mcp/tools/calculated_metrics.py
adobe_cja_mcp/tools/dimensions.py
adobe_cja_mcp/tools/metrics.py
adobe_cja_mcp/tools/reporting.py
adobe_cja_mcp/tools/segments.py
adobe_cja_mcp/utils/__init__.py
adobe_cja_mcp/utils/config.py
adobe_cja_mcp-0.1.2.dist-info/licenses/LICENSE
adobe_cja_mcp-0.1.2.dist-info/METADATA
adobe_cja_mcp-0.1.2.dist-info/WHEEL
adobe_cja_mcp-0.1.2.dist-info/entry_points.txt
adobe_cja_mcp-0.1.2.dist-info/top_level.txt
adobe_cja_mcp-0.1.2.dist-info/RECORD
