Metadata-Version: 2.4
Name: adobe-cja-mcp
Version: 0.1.2
Summary: Model Context Protocol server for Adobe Customer Journey Analytics
Author-email: Mark Hilton <mark.hilton@bhn.com>
License: MIT
Project-URL: Homepage, https://github.com/markhilton/adobe-cja-mcp
Project-URL: Documentation, https://github.com/markhilton/adobe-cja-mcp#readme
Project-URL: Repository, https://github.com/markhilton/adobe-cja-mcp
Project-URL: Issues, https://github.com/markhilton/adobe-cja-mcp/issues
Keywords: adobe,cja,customer-journey-analytics,mcp,model-context-protocol,analytics
Classifier: Development Status :: 4 - Beta
Classifier: Intended Audience :: Developers
Classifier: License :: OSI Approved :: MIT License
Classifier: Programming Language :: Python :: 3
Classifier: Programming Language :: Python :: 3.10
Classifier: Programming Language :: Python :: 3.11
Classifier: Programming Language :: Python :: 3.12
Classifier: Topic :: Software Development :: Libraries :: Python Modules
Requires-Python: >=3.10
License-File: LICENSE
Requires-Dist: mcp>=1.0.0
Requires-Dist: httpx>=0.27.0
Requires-Dist: python-dotenv>=1.0.0
Requires-Dist: pydantic>=2.0.0
Requires-Dist: pydantic-settings>=2.0.0
Provides-Extra: dev
Requires-Dist: pytest>=8.0.0; extra == "dev"
Requires-Dist: pytest-asyncio>=0.23.0; extra == "dev"
Requires-Dist: pytest-cov>=4.1.0; extra == "dev"
Requires-Dist: pytest-mock>=3.12.0; extra == "dev"
Requires-Dist: black>=24.0.0; extra == "dev"
Requires-Dist: ruff>=0.3.0; extra == "dev"
Requires-Dist: mypy>=1.8.0; extra == "dev"
Dynamic: license-file
